base/BaseCrawl.py
base/CreateCrawl.py
base/__init__.py
netcrawl/BaseCrawl.py
netcrawl/CreateCrawl.py
netcrawl/__init__.py
netcrawl-1.2.1.dist-info/LICENSE
netcrawl-1.2.1.dist-info/METADATA
netcrawl-1.2.1.dist-info/WHEEL
netcrawl-1.2.1.dist-info/top_level.txt
netcrawl-1.2.1.dist-info/RECORD
