Metadata-Version: 2.1
Name: netcrawl
Version: 1.2.1
Summary: support 
Home-page: https://github.com/Eilison/NetCrawl.git
Author: eilison
Author-email: 1277886419@qq.com
License: MIT License
Platform: all
Requires-Dist: selenium
